<databaseChangeLog xmlns="http://www.liquibase.org/xml/ns/dbchangelog"
                   xmlns:xsi="http://www.w3.org/2001/XMLSchema-instance"
                   xsi:schemaLocation="http://www.liquibase.org/xml/ns/dbchangelog http://www.liquibase.org/xml/ns/dbchangelog/dbchangelog-latest.xsd">

    <changeSet id="1-create-trucks-table" author="adragin">
        <createTable tableName="trucks">
            <column name="id" type="UUID">
                <constraints primaryKey="true" nullable="false"/>
            </column>
            <column name="length" type="INTEGER">
                <constraints nullable="false"/>
            </column>
            <column name="weight" type="INTEGER">
                <constraints nullable="false"/>
            </column>
            <column name="capacity" type="DECIMAL(10, 2)">
                <constraints nullable="false"/>
            </column>
            <column name="truck_status" type="VARCHAR(50)">
                <constraints nullable="false"/>
            </column>
            <column name="location" type="VARCHAR(255)">
                <constraints nullable="true"/>
            </column>
            <column name="truck_type_id" type="UUID">
                <constraints nullable="false"/>
            </column>
        </createTable>

        <!-- Foreign key for 'truck_type_id' -->
        <addForeignKeyConstraint baseTableName="trucks"
                                 baseColumnNames="truck_type_id"
                                 constraintName="fk_trucks_truck_type_id"
                                 referencedTableName="truck_types"
                                 referencedColumnNames="id"
                                 onDelete="CASCADE"/>
    </changeSet>

    <!-- Constraint for 'truck_status' -->
    <changeSet id="2-add-check-constraints-for-trucks-table" author="adragin">
        <sql>
            ALTER TABLE trucks
                ADD CONSTRAINT chk_truck_status CHECK (truck_status IN
                                                       ('AVAILABLE', 'IN_TRANSIT', 'LOADING', 'UNLOADING', 'UNAVAILABLE',
                                                        'DELETED'));
        </sql>
    </changeSet>

</databaseChangeLog>
